ainu_utils-0.5.0.dist-info/METADATA
ainu_utils-0.5.0.dist-info/WHEEL
ainu_utils/__init__.py
ainu_utils/__init__.pyi
ainu_utils/ainu_utils.cpython-312-powerpc64le-linux-gnu.so
ainu_utils/py.typed
ainu_utils-0.5.0.dist-info/RECORD
