Metadata-Version: 2.4
Name: ainu-utils
Version: 0.5.0
Requires-Dist: pytest==8.1.1 ; extra == 'test'
Requires-Dist: ruff==0.3.3 ; extra == 'dev'
Requires-Dist: mypy==1.9.0 ; extra == 'dev'
Provides-Extra: test
Provides-Extra: dev
Summary: A collection of utility for with the Ainu language
License: MIT
Requires-Python: >=3.8
